package com.google.android.gms.internal;

import java.io.IOException;
import java.util.Map;
import java.util.TreeMap;
import org.apache.http.Header;
import org.apache.http.HttpEntity;

public final class zzad implements zzk {
  private static boolean DEBUG = zzab.DEBUG;
  
  private static int zzbm = 3000;
  
  private static int zzbn = 4096;
  
  private zzan zzbo;
  
  private zzae zzbp;
  
  public zzad(zzan paramzzan) {
    this(paramzzan, new zzae(zzbn));
  }
  
  private zzad(zzan paramzzan, zzae paramzzae) {
    this.zzbo = paramzzan;
    this.zzbp = paramzzae;
  }
  
  private static Map<String, String> zza(Header[] paramArrayOfHeader) {
    TreeMap<String, Object> treeMap = new TreeMap<String, Object>(String.CASE_INSENSITIVE_ORDER);
    for (byte b = 0; b < paramArrayOfHeader.length; b++)
      treeMap.put(paramArrayOfHeader[b].getName(), paramArrayOfHeader[b].getValue()); 
    return (Map)treeMap;
  }
  
  private static void zza(String paramString, zzp<?> paramzzp, zzaa paramzzaa) throws zzaa {
    zzx zzx = paramzzp.zzj();
    int i = paramzzp.zzi();
    try {
      zzx.zza(paramzzaa);
      paramzzp.zzb(String.format("%s-retry [timeout=%s]", new Object[] { paramString, Integer.valueOf(i) }));
      return;
    } catch (zzaa zzaa1) {
      paramzzp.zzb(String.format("%s-timeout-giveup [timeout=%s]", new Object[] { paramString, Integer.valueOf(i) }));
      throw zzaa1;
    } 
  }
  
  private final byte[] zza(HttpEntity paramHttpEntity) throws IOException, zzy {
    // Byte code:
    //   0: new com/google/android/gms/internal/zzaq
    //   3: dup
    //   4: aload_0
    //   5: getfield zzbp : Lcom/google/android/gms/internal/zzae;
    //   8: aload_1
    //   9: invokeinterface getContentLength : ()J
    //   14: l2i
    //   15: invokespecial <init> : (Lcom/google/android/gms/internal/zzae;I)V
    //   18: astore_2
    //   19: aconst_null
    //   20: astore_3
    //   21: aload_3
    //   22: astore #4
    //   24: aload_1
    //   25: invokeinterface getContent : ()Ljava/io/InputStream;
    //   30: astore #5
    //   32: aload #5
    //   34: ifnull -> 125
    //   37: aload_3
    //   38: astore #4
    //   40: aload_0
    //   41: getfield zzbp : Lcom/google/android/gms/internal/zzae;
    //   44: sipush #1024
    //   47: invokevirtual zzb : (I)[B
    //   50: astore_3
    //   51: aload_3
    //   52: astore #4
    //   54: aload #5
    //   56: aload_3
    //   57: invokevirtual read : ([B)I
    //   60: istore #6
    //   62: iload #6
    //   64: iconst_m1
    //   65: if_icmpeq -> 82
    //   68: aload_3
    //   69: astore #4
    //   71: aload_2
    //   72: aload_3
    //   73: iconst_0
    //   74: iload #6
    //   76: invokevirtual write : ([BII)V
    //   79: goto -> 51
    //   82: aload_3
    //   83: astore #4
    //   85: aload_2
    //   86: invokevirtual toByteArray : ()[B
    //   89: astore #5
    //   91: aload_1
    //   92: invokeinterface consumeContent : ()V
    //   97: goto -> 110
    //   100: astore_1
    //   101: ldc 'Error occured when calling consumingContent'
    //   103: iconst_0
    //   104: anewarray java/lang/Object
    //   107: invokestatic zza : (Ljava/lang/String;[Ljava/lang/Object;)V
    //   110: aload_0
    //   111: getfield zzbp : Lcom/google/android/gms/internal/zzae;
    //   114: aload_3
    //   115: invokevirtual zza : ([B)V
    //   118: aload_2
    //   119: invokevirtual close : ()V
    //   122: aload #5
    //   124: areturn
    //   125: aload_3
    //   126: astore #4
    //   128: new com/google/android/gms/internal/zzy
    //   131: astore #5
    //   133: aload_3
    //   134: astore #4
    //   136: aload #5
    //   138: invokespecial <init> : ()V
    //   141: aload_3
    //   142: astore #4
    //   144: aload #5
    //   146: athrow
    //   147: astore_3
    //   148: aload_1
    //   149: invokeinterface consumeContent : ()V
    //   154: goto -> 167
    //   157: astore_1
    //   158: ldc 'Error occured when calling consumingContent'
    //   160: iconst_0
    //   161: anewarray java/lang/Object
    //   164: invokestatic zza : (Ljava/lang/String;[Ljava/lang/Object;)V
    //   167: aload_0
    //   168: getfield zzbp : Lcom/google/android/gms/internal/zzae;
    //   171: aload #4
    //   173: invokevirtual zza : ([B)V
    //   176: aload_2
    //   177: invokevirtual close : ()V
    //   180: goto -> 185
    //   183: aload_3
    //   184: athrow
    //   185: goto -> 183
    // Exception table:
    //   from	to	target	type
    //   24	32	147	finally
    //   40	51	147	finally
    //   54	62	147	finally
    //   71	79	147	finally
    //   85	91	147	finally
    //   91	97	100	java/io/IOException
    //   128	133	147	finally
    //   136	141	147	finally
    //   144	147	147	finally
    //   148	154	157	java/io/IOException
  }
  
  public final zzn zza(zzp<?> paramzzp) throws zzaa {
    // Byte code:
    //   0: invokestatic elapsedRealtime : ()J
    //   3: lstore_2
    //   4: invokestatic emptyMap : ()Ljava/util/Map;
    //   7: astore #4
    //   9: aconst_null
    //   10: astore #5
    //   12: aconst_null
    //   13: astore #6
    //   15: new java/util/HashMap
    //   18: astore #7
    //   20: aload #7
    //   22: invokespecial <init> : ()V
    //   25: aload_1
    //   26: invokevirtual zze : ()Lcom/google/android/gms/internal/zzc;
    //   29: astore #8
    //   31: aload #8
    //   33: ifnull -> 100
    //   36: aload #8
    //   38: getfield zza : Ljava/lang/String;
    //   41: astore #9
    //   43: aload #9
    //   45: ifnull -> 60
    //   48: aload #7
    //   50: ldc 'If-None-Match'
    //   52: aload #9
    //   54: invokeinterface put : (Ljava/lang/Object;Ljava/lang/Object;)Ljava/lang/Object;
    //   59: pop
    //   60: aload #8
    //   62: getfield zzc : J
    //   65: lconst_0
    //   66: lcmp
    //   67: ifle -> 100
    //   70: new java/util/Date
    //   73: astore #9
    //   75: aload #9
    //   77: aload #8
    //   79: getfield zzc : J
    //   82: invokespecial <init> : (J)V
    //   85: aload #7
    //   87: ldc 'If-Modified-Since'
    //   89: aload #9
    //   91: invokestatic formatDate : (Ljava/util/Date;)Ljava/lang/String;
    //   94: invokeinterface put : (Ljava/lang/Object;Ljava/lang/Object;)Ljava/lang/Object;
    //   99: pop
    //   100: aload_0
    //   101: getfield zzbo : Lcom/google/android/gms/internal/zzan;
    //   104: aload_1
    //   105: aload #7
    //   107: invokeinterface zza : (Lcom/google/android/gms/internal/zzp;Ljava/util/Map;)Lorg/apache/http/HttpResponse;
    //   112: astore #8
    //   114: aload #4
    //   116: astore #9
    //   118: aload #6
    //   120: astore #5
    //   122: aload #8
    //   124: invokeinterface getStatusLine : ()Lorg/apache/http/StatusLine;
    //   129: astore #10
    //   131: aload #4
    //   133: astore #9
    //   135: aload #6
    //   137: astore #5
    //   139: aload #10
    //   141: invokeinterface getStatusCode : ()I
    //   146: istore #11
    //   148: aload #4
    //   150: astore #9
    //   152: aload #6
    //   154: astore #5
    //   156: aload #8
    //   158: invokeinterface getAllHeaders : ()[Lorg/apache/http/Header;
    //   163: invokestatic zza : ([Lorg/apache/http/Header;)Ljava/util/Map;
    //   166: astore #7
    //   168: iload #11
    //   170: sipush #304
    //   173: if_icmpne -> 278
    //   176: aload #7
    //   178: astore #9
    //   180: aload #6
    //   182: astore #5
    //   184: aload_1
    //   185: invokevirtual zze : ()Lcom/google/android/gms/internal/zzc;
    //   188: astore #4
    //   190: aload #4
    //   192: ifnonnull -> 223
    //   195: aload #7
    //   197: astore #9
    //   199: aload #6
    //   201: astore #5
    //   203: new com/google/android/gms/internal/zzn
    //   206: dup
    //   207: sipush #304
    //   210: aconst_null
    //   211: aload #7
    //   213: iconst_1
    //   214: invokestatic elapsedRealtime : ()J
    //   217: lload_2
    //   218: lsub
    //   219: invokespecial <init> : (I[BLjava/util/Map;ZJ)V
    //   222: areturn
    //   223: aload #7
    //   225: astore #9
    //   227: aload #6
    //   229: astore #5
    //   231: aload #4
    //   233: getfield zzf : Ljava/util/Map;
    //   236: aload #7
    //   238: invokeinterface putAll : (Ljava/util/Map;)V
    //   243: aload #7
    //   245: astore #9
    //   247: aload #6
    //   249: astore #5
    //   251: new com/google/android/gms/internal/zzn
    //   254: dup
    //   255: sipush #304
    //   258: aload #4
    //   260: getfield data : [B
    //   263: aload #4
    //   265: getfield zzf : Ljava/util/Map;
    //   268: iconst_1
    //   269: invokestatic elapsedRealtime : ()J
    //   272: lload_2
    //   273: lsub
    //   274: invokespecial <init> : (I[BLjava/util/Map;ZJ)V
    //   277: areturn
    //   278: aload #7
    //   280: astore #9
    //   282: aload #6
    //   284: astore #5
    //   286: aload #8
    //   288: invokeinterface getEntity : ()Lorg/apache/http/HttpEntity;
    //   293: ifnull -> 320
    //   296: aload #7
    //   298: astore #9
    //   300: aload #6
    //   302: astore #5
    //   304: aload_0
    //   305: aload #8
    //   307: invokeinterface getEntity : ()Lorg/apache/http/HttpEntity;
    //   312: invokespecial zza : (Lorg/apache/http/HttpEntity;)[B
    //   315: astore #4
    //   317: goto -> 333
    //   320: aload #7
    //   322: astore #9
    //   324: aload #6
    //   326: astore #5
    //   328: iconst_0
    //   329: newarray byte
    //   331: astore #4
    //   333: aload #7
    //   335: astore #9
    //   337: aload #4
    //   339: astore #5
    //   341: invokestatic elapsedRealtime : ()J
    //   344: lload_2
    //   345: lsub
    //   346: lstore #12
    //   348: aload #7
    //   350: astore #9
    //   352: aload #4
    //   354: astore #5
    //   356: getstatic com/google/android/gms/internal/zzad.DEBUG : Z
    //   359: istore #14
    //   361: iload #14
    //   363: ifne -> 411
    //   366: getstatic com/google/android/gms/internal/zzad.zzbm : I
    //   369: istore #15
    //   371: lload #12
    //   373: iload #15
    //   375: i2l
    //   376: lcmp
    //   377: ifle -> 383
    //   380: goto -> 411
    //   383: goto -> 520
    //   386: astore #5
    //   388: aload #7
    //   390: astore #9
    //   392: aload #4
    //   394: astore #7
    //   396: aload #5
    //   398: astore #4
    //   400: aload #8
    //   402: astore #5
    //   404: aload #9
    //   406: astore #8
    //   408: goto -> 656
    //   411: aload #4
    //   413: ifnull -> 452
    //   416: aload #4
    //   418: astore #5
    //   420: aload #5
    //   422: arraylength
    //   423: invokestatic valueOf : (I)Ljava/lang/Integer;
    //   426: astore #9
    //   428: goto -> 461
    //   431: astore #4
    //   433: aload #7
    //   435: astore #9
    //   437: aload #5
    //   439: astore #7
    //   441: aload #8
    //   443: astore #5
    //   445: aload #9
    //   447: astore #8
    //   449: goto -> 656
    //   452: aload #4
    //   454: astore #5
    //   456: ldc_w 'null'
    //   459: astore #9
    //   461: aload #4
    //   463: astore #5
    //   465: ldc_w 'HTTP response for request=<%s> [lifetime=%d], [size=%s], [rc=%d], [retryCount=%s]'
    //   468: iconst_5
    //   469: anewarray java/lang/Object
    //   472: dup
    //   473: iconst_0
    //   474: aload_1
    //   475: aastore
    //   476: dup
    //   477: iconst_1
    //   478: lload #12
    //   480: invokestatic valueOf : (J)Ljava/lang/Long;
    //   483: aastore
    //   484: dup
    //   485: iconst_2
    //   486: aload #9
    //   488: aastore
    //   489: dup
    //   490: iconst_3
    //   491: aload #10
    //   493: invokeinterface getStatusCode : ()I
    //   498: invokestatic valueOf : (I)Ljava/lang/Integer;
    //   501: aastore
    //   502: dup
    //   503: iconst_4
    //   504: aload_1
    //   505: invokevirtual zzj : ()Lcom/google/android/gms/internal/zzx;
    //   508: invokeinterface zzb : ()I
    //   513: invokestatic valueOf : (I)Ljava/lang/Integer;
    //   516: aastore
    //   517: invokestatic zzb : (Ljava/lang/String;[Ljava/lang/Object;)V
    //   520: iload #11
    //   522: sipush #200
    //   525: if_icmplt -> 577
    //   528: iload #11
    //   530: sipush #299
    //   533: if_icmpgt -> 577
    //   536: aload #4
    //   538: astore #5
    //   540: invokestatic elapsedRealtime : ()J
    //   543: lstore #12
    //   545: aload #4
    //   547: astore #5
    //   549: aload #7
    //   551: astore #9
    //   553: new com/google/android/gms/internal/zzn
    //   556: dup
    //   557: iload #11
    //   559: aload #4
    //   561: aload #7
    //   563: iconst_0
    //   564: lload #12
    //   566: lload_2
    //   567: lsub
    //   568: invokespecial <init> : (I[BLjava/util/Map;ZJ)V
    //   571: areturn
    //   572: astore #4
    //   574: goto -> 624
    //   577: aload #7
    //   579: astore #9
    //   581: aload #4
    //   583: astore #5
    //   585: new java/io/IOException
    //   588: astore #6
    //   590: aload #7
    //   592: astore #9
    //   594: aload #4
    //   596: astore #5
    //   598: aload #6
    //   600: invokespecial <init> : ()V
    //   603: aload #7
    //   605: astore #9
    //   607: aload #4
    //   609: astore #5
    //   611: aload #6
    //   613: athrow
    //   614: astore_1
    //   615: goto -> 624
    //   618: astore #4
    //   620: aload #9
    //   622: astore #7
    //   624: aload #7
    //   626: astore #9
    //   628: aload #5
    //   630: astore #7
    //   632: aload #8
    //   634: astore #5
    //   636: aload #9
    //   638: astore #8
    //   640: goto -> 656
    //   643: astore #9
    //   645: aconst_null
    //   646: astore #7
    //   648: aload #4
    //   650: astore #8
    //   652: aload #9
    //   654: astore #4
    //   656: aload #5
    //   658: ifnull -> 846
    //   661: aload #5
    //   663: invokeinterface getStatusLine : ()Lorg/apache/http/StatusLine;
    //   668: invokeinterface getStatusCode : ()I
    //   673: istore #11
    //   675: ldc_w 'Unexpected response code %d for %s'
    //   678: iconst_2
    //   679: anewarray java/lang/Object
    //   682: dup
    //   683: iconst_0
    //   684: iload #11
    //   686: invokestatic valueOf : (I)Ljava/lang/Integer;
    //   689: aastore
    //   690: dup
    //   691: iconst_1
    //   692: aload_1
    //   693: invokevirtual getUrl : ()Ljava/lang/String;
    //   696: aastore
    //   697: invokestatic zzc : (Ljava/lang/String;[Ljava/lang/Object;)V
    //   700: aload #7
    //   702: ifnull -> 829
    //   705: new com/google/android/gms/internal/zzn
    //   708: dup
    //   709: iload #11
    //   711: aload #7
    //   713: aload #8
    //   715: iconst_0
    //   716: invokestatic elapsedRealtime : ()J
    //   719: lload_2
    //   720: lsub
    //   721: invokespecial <init> : (I[BLjava/util/Map;ZJ)V
    //   724: astore #4
    //   726: iload #11
    //   728: sipush #401
    //   731: if_icmpeq -> 810
    //   734: iload #11
    //   736: sipush #403
    //   739: if_icmpne -> 745
    //   742: goto -> 810
    //   745: iload #11
    //   747: sipush #400
    //   750: if_icmplt -> 774
    //   753: iload #11
    //   755: sipush #499
    //   758: if_icmple -> 764
    //   761: goto -> 774
    //   764: new com/google/android/gms/internal/zzf
    //   767: dup
    //   768: aload #4
    //   770: invokespecial <init> : (Lcom/google/android/gms/internal/zzn;)V
    //   773: athrow
    //   774: iload #11
    //   776: sipush #500
    //   779: if_icmplt -> 800
    //   782: iload #11
    //   784: sipush #599
    //   787: if_icmpgt -> 800
    //   790: new com/google/android/gms/internal/zzy
    //   793: dup
    //   794: aload #4
    //   796: invokespecial <init> : (Lcom/google/android/gms/internal/zzn;)V
    //   799: athrow
    //   800: new com/google/android/gms/internal/zzy
    //   803: dup
    //   804: aload #4
    //   806: invokespecial <init> : (Lcom/google/android/gms/internal/zzn;)V
    //   809: athrow
    //   810: new com/google/android/gms/internal/zza
    //   813: dup
    //   814: aload #4
    //   816: invokespecial <init> : (Lcom/google/android/gms/internal/zzn;)V
    //   819: astore #4
    //   821: ldc_w 'auth'
    //   824: astore #5
    //   826: goto -> 941
    //   829: new com/google/android/gms/internal/zzm
    //   832: dup
    //   833: invokespecial <init> : ()V
    //   836: astore #4
    //   838: ldc_w 'network'
    //   841: astore #5
    //   843: goto -> 941
    //   846: new com/google/android/gms/internal/zzo
    //   849: dup
    //   850: aload #4
    //   852: invokespecial <init> : (Ljava/lang/Throwable;)V
    //   855: athrow
    //   856: astore #4
    //   858: aload_1
    //   859: invokevirtual getUrl : ()Ljava/lang/String;
    //   862: invokestatic valueOf : (Ljava/lang/Object;)Ljava/lang/String;
    //   865: astore_1
    //   866: aload_1
    //   867: invokevirtual length : ()I
    //   870: ifeq -> 884
    //   873: ldc_w 'Bad URL '
    //   876: aload_1
    //   877: invokevirtual concat : (Ljava/lang/String;)Ljava/lang/String;
    //   880: astore_1
    //   881: goto -> 895
    //   884: new java/lang/String
    //   887: dup
    //   888: ldc_w 'Bad URL '
    //   891: invokespecial <init> : (Ljava/lang/String;)V
    //   894: astore_1
    //   895: new java/lang/RuntimeException
    //   898: dup
    //   899: aload_1
    //   900: aload #4
    //   902: invokespecial <init> : (Ljava/lang/String;Ljava/lang/Throwable;)V
    //   905: athrow
    //   906: astore #4
    //   908: new com/google/android/gms/internal/zzz
    //   911: dup
    //   912: invokespecial <init> : ()V
    //   915: astore #4
    //   917: ldc_w 'connection'
    //   920: astore #5
    //   922: goto -> 941
    //   925: astore #4
    //   927: new com/google/android/gms/internal/zzz
    //   930: dup
    //   931: invokespecial <init> : ()V
    //   934: astore #4
    //   936: ldc_w 'socket'
    //   939: astore #5
    //   941: aload #5
    //   943: aload_1
    //   944: aload #4
    //   946: invokestatic zza : (Ljava/lang/String;Lcom/google/android/gms/internal/zzp;Lcom/google/android/gms/internal/zzaa;)V
    //   949: goto -> 4
    // Exception table:
    //   from	to	target	type
    //   15	31	925	java/net/SocketTimeoutException
    //   15	31	906	org/apache/http/conn/ConnectTimeoutException
    //   15	31	856	java/net/MalformedURLException
    //   15	31	643	java/io/IOException
    //   36	43	925	java/net/SocketTimeoutException
    //   36	43	906	org/apache/http/conn/ConnectTimeoutException
    //   36	43	856	java/net/MalformedURLException
    //   36	43	643	java/io/IOException
    //   48	60	925	java/net/SocketTimeoutException
    //   48	60	906	org/apache/http/conn/ConnectTimeoutException
    //   48	60	856	java/net/MalformedURLException
    //   48	60	643	java/io/IOException
    //   60	100	925	java/net/SocketTimeoutException
    //   60	100	906	org/apache/http/conn/ConnectTimeoutException
    //   60	100	856	java/net/MalformedURLException
    //   60	100	643	java/io/IOException
    //   100	114	925	java/net/SocketTimeoutException
    //   100	114	906	org/apache/http/conn/ConnectTimeoutException
    //   100	114	856	java/net/MalformedURLException
    //   100	114	643	java/io/IOException
    //   122	131	925	java/net/SocketTimeoutException
    //   122	131	906	org/apache/http/conn/ConnectTimeoutException
    //   122	131	856	java/net/MalformedURLException
    //   122	131	618	java/io/IOException
    //   139	148	925	java/net/SocketTimeoutException
    //   139	148	906	org/apache/http/conn/ConnectTimeoutException
    //   139	148	856	java/net/MalformedURLException
    //   139	148	618	java/io/IOException
    //   156	168	925	java/net/SocketTimeoutException
    //   156	168	906	org/apache/http/conn/ConnectTimeoutException
    //   156	168	856	java/net/MalformedURLException
    //   156	168	618	java/io/IOException
    //   184	190	925	java/net/SocketTimeoutException
    //   184	190	906	org/apache/http/conn/ConnectTimeoutException
    //   184	190	856	java/net/MalformedURLException
    //   184	190	618	java/io/IOException
    //   203	223	925	java/net/SocketTimeoutException
    //   203	223	906	org/apache/http/conn/ConnectTimeoutException
    //   203	223	856	java/net/MalformedURLException
    //   203	223	618	java/io/IOException
    //   231	243	925	java/net/SocketTimeoutException
    //   231	243	906	org/apache/http/conn/ConnectTimeoutException
    //   231	243	856	java/net/MalformedURLException
    //   231	243	618	java/io/IOException
    //   251	278	925	java/net/SocketTimeoutException
    //   251	278	906	org/apache/http/conn/ConnectTimeoutException
    //   251	278	856	java/net/MalformedURLException
    //   251	278	618	java/io/IOException
    //   286	296	925	java/net/SocketTimeoutException
    //   286	296	906	org/apache/http/conn/ConnectTimeoutException
    //   286	296	856	java/net/MalformedURLException
    //   286	296	618	java/io/IOException
    //   304	317	925	java/net/SocketTimeoutException
    //   304	317	906	org/apache/http/conn/ConnectTimeoutException
    //   304	317	856	java/net/MalformedURLException
    //   304	317	618	java/io/IOException
    //   328	333	925	java/net/SocketTimeoutException
    //   328	333	906	org/apache/http/conn/ConnectTimeoutException
    //   328	333	856	java/net/MalformedURLException
    //   328	333	618	java/io/IOException
    //   341	348	925	java/net/SocketTimeoutException
    //   341	348	906	org/apache/http/conn/ConnectTimeoutException
    //   341	348	856	java/net/MalformedURLException
    //   341	348	618	java/io/IOException
    //   356	361	925	java/net/SocketTimeoutException
    //   356	361	906	org/apache/http/conn/ConnectTimeoutException
    //   356	361	856	java/net/MalformedURLException
    //   356	361	618	java/io/IOException
    //   366	371	925	java/net/SocketTimeoutException
    //   366	371	906	org/apache/http/conn/ConnectTimeoutException
    //   366	371	856	java/net/MalformedURLException
    //   366	371	386	java/io/IOException
    //   420	428	925	java/net/SocketTimeoutException
    //   420	428	906	org/apache/http/conn/ConnectTimeoutException
    //   420	428	856	java/net/MalformedURLException
    //   420	428	431	java/io/IOException
    //   465	520	925	java/net/SocketTimeoutException
    //   465	520	906	org/apache/http/conn/ConnectTimeoutException
    //   465	520	856	java/net/MalformedURLException
    //   465	520	572	java/io/IOException
    //   540	545	925	java/net/SocketTimeoutException
    //   540	545	906	org/apache/http/conn/ConnectTimeoutException
    //   540	545	856	java/net/MalformedURLException
    //   540	545	572	java/io/IOException
    //   553	572	925	java/net/SocketTimeoutException
    //   553	572	906	org/apache/http/conn/ConnectTimeoutException
    //   553	572	856	java/net/MalformedURLException
    //   553	572	618	java/io/IOException
    //   585	590	925	java/net/SocketTimeoutException
    //   585	590	906	org/apache/http/conn/ConnectTimeoutException
    //   585	590	856	java/net/MalformedURLException
    //   585	590	618	java/io/IOException
    //   598	603	925	java/net/SocketTimeoutException
    //   598	603	906	org/apache/http/conn/ConnectTimeoutException
    //   598	603	856	java/net/MalformedURLException
    //   598	603	618	java/io/IOException
    //   611	614	925	java/net/SocketTimeoutException
    //   611	614	906	org/apache/http/conn/ConnectTimeoutException
    //   611	614	856	java/net/MalformedURLException
    //   611	614	618	java/io/IOException
  }
}


/* Location:              /home/dragonh/workspace/work/app/apk-reverse/dex-tools-2.1/target-dex2jar.jar!/com/google/android/gms/internal/zzad.class
 * Java compiler version: 6 (50.0)
 * JD-Core Version:       1.1.3
 */